odoo10_addon_user_immutable-10.0.1.0.0-py2.7-nspkg.pth
odoo/addons/user_immutable/README.rst
odoo/addons/user_immutable/__init__.py
odoo/addons/user_immutable/__manifest__.py
odoo/addons/user_immutable/data/user_immutable_data.xml
odoo/addons/user_immutable/demo/user_immutable_demo.xml
odoo/addons/user_immutable/models/__init__.py
odoo/addons/user_immutable/models/res_groups.py
odoo/addons/user_immutable/models/res_users.py
odoo/addons/user_immutable/tests/__init__.py
odoo/addons/user_immutable/tests/test_res_groups.py
odoo/addons/user_immutable/tests/test_res_users.py
odoo10_addon_user_immutable-10.0.1.0.0.dist-info/DESCRIPTION.rst
odoo10_addon_user_immutable-10.0.1.0.0.dist-info/METADATA
odoo10_addon_user_immutable-10.0.1.0.0.dist-info/RECORD
odoo10_addon_user_immutable-10.0.1.0.0.dist-info/WHEEL
odoo10_addon_user_immutable-10.0.1.0.0.dist-info/metadata.json
odoo10_addon_user_immutable-10.0.1.0.0.dist-info/namespace_packages.txt
odoo10_addon_user_immutable-10.0.1.0.0.dist-info/top_level.txt
